pyclt
