Metadata-Version: 1.0
Name: pyclt
Version: 0.7.2
Summary: 一个快捷的命令行翻译软件!按照GPL-3.0协议开源!
Home-page: https://github.com/zsh2401/PYCLT
Author: zsh2401
Author-email: zsh2401@163.com
License: UNKNOWN
Platform: UNKNOWN
